[
    {
        "title": "СМИ сообщили о закрытии магазинов подарков \"Красный куб\" ",
        "additionally": "Мужчина упаковывает подарок",
        "href": "https://ria.ru/20200302/1566717642.html",
        "time": "12:09"
    },
    {
        "title": "Стало известно, когда Белоруссия начнет получать азербайджанскую нефть ",
        "additionally": "Танкер",
        "href": "https://radiosputnik.ria.ru/20200302/1566692249.html",
        "time": "11:53"
    },
    {
        "title": "Артюхов принял участие в совещании по льготам для проектов в Арктике ",
        "additionally": "Губернатор Ямало-Ненецкого автономного округа Дмитрий Артюхов",
        "href": "https://ria.ru/20200302/1566678341.html",
        "time": "11:46"
    },
    {
        "title": "Азербайджан 5-6 марта направит танкер с нефтью для Белоруссии ",
        "additionally": "Танкер",
        "href": "https://ria.ru/20200302/1566674510.html",
        "time": "11:34"
    },
    {
        "title": "Российские миллиардеры с начала года потеряли почти $30 миллиардов ",
        "additionally": "Американские доллары",
        "href": "https://ria.ru/20200302/1566652028.html",
        "time": "10:32"
    },
    {
        "title": "У вас есть долги по кредитам? ",
        "additionally": "Менеджер в офисе по обслуживанию физических лиц ПАО Сбербанк",
        "href": "https://ria.ru/20200302/1566634045.html",
        "time": "09:37"
    },
    {
        "title": "Aurus планирует изменения в акционерной структуре ",
        "additionally": "генеральный директор Aurus Адиль Ширинов",
        "href": "https://ria.ru/20200302/1566631091.html",
        "time": "09:27"
    },
    {
        "title": "Мишустин поручил при подготовке бюджета учесть риски на фоне COVID-19 ",
        "additionally": "Председатель правительства РФ Михаил Мишустин проводит оперативное совещание с членами правительства РФ",
        "href": "https://ria.ru/20200302/1566627693.html",
        "time": "09:17"
    },
    {
        "title": "Федор Бондарчук стал официальным лицом бренда Газпромбанка ",
        "additionally": "Режиссер и продюсер Федор Бондарчук",
        "href": "https://ria.ru/20200302/1566626455.html",
        "time": "09:13"
    },
    {
        "title": "Aurus со временем предложит покупателям несколько вариантов двигателей ",
        "additionally": "Автомобиль Aurus",
        "href": "https://ria.ru/20200302/1566614109.html",
        "time": "09:00"
    }
]