[
    {
        "title": "Центробанк сохранил ключевую ставку ",
        "additionally": "Здание Центрального банка РФ",
        "href": "https://ria.ru/20200320/1568927003.html",
        "time": "20:12"
    },
    {
        "title": "ЦБ попросил банки информировать людей о мерах защиты от коронавируса ",
        "additionally": "Санитарная обработка общественного транспорта",
        "href": "https://ria.ru/20200320/1568925095.html",
        "time": "19:32"
    },
    {
        "title": "К газопроводу \"Северный поток-2\" увеличили мощность подвода ",
        "additionally": "Строительство газопровода Северный поток-2",
        "href": "https://radiosputnik.ria.ru/20200320/1568924968.html",
        "time": "19:32"
    },
    {
        "title": "\"Дом.РФ\" не ожидает значительного изменения ипотечных ставок ",
        "additionally": "Жилой район",
        "href": "https://realty.ria.ru/20200320/1568924830.html",
        "time": "19:30"
    },
    {
        "title": "Эксперт оценил влияние коронавируса на южнокорейскую экономику ",
        "additionally": "Измерение температуры водителя автомобиля в Сеуле",
        "href": "https://ria.ru/20200320/1568924719.html",
        "time": "19:25"
    },
    {
        "title": "Минфин США продлил отсрочку ограничений в отношении \"Группы ГАЗ\" ",
        "additionally": "Здание министерства финансов США в Вашингтоне",
        "href": "https://radiosputnik.ria.ru/20200320/1568924596.html",
        "time": "19:22"
    },
    {
        "title": "Правительство готово субсидировать ставки по кредитам застройщиков ",
        "additionally": "Премьер-министр РФ М. Мишустин провел заседание Координационного совета по борьбе с коронавирусной инфекцией",
        "href": "https://realty.ria.ru/20200320/1568923771.html",
        "time": "19:10"
    },
    {
        "title": "Тамбовская область и РЖД подписали новое соглашение о сотрудничестве ",
        "additionally": "Стенд ОАО РЖД",
        "href": "https://ria.ru/20200320/1568923495.html",
        "time": "19:04"
    },
    {
        "title": "Перевозчиков ТКО Ленобласти и Петербурга проконтролируют онлайн ",
        "additionally": "Спрессованные жестяные банки ",
        "href": "https://ria.ru/20200320/1568922826.html",
        "time": "18:53"
    },
    {
        "title": "США продлили отсрочку введения санкций по \"Группе ГАЗ\" ",
        "additionally": "Министерство финансов США в Вашингтоне",
        "href": "https://ria.ru/20200320/1568922718.html",
        "time": "18:52"
    }
]