[
    {
        "title": "Способное достроить \"Северный поток – 2\" судно покинуло порт Находки ",
        "additionally": "Город Находка в Приморском крае",
        "href": "https://ria.ru/20200209/1564466593.html",
        "time": "22:22"
    },
    {
        "title": "Первое судно с цитрусовыми готовится к отправке из Сирии в Россию ",
        "additionally": "Апельсины",
        "href": "https://ria.ru/20200209/1564460976.html",
        "time": "17:33"
    },
    {
        "title": "В армянской \"дочке\" РЖД сменился руководитель ",
        "additionally": "Логотип РЖД",
        "href": "https://ria.ru/20200209/1564460531.html",
        "time": "17:16"
    },
    {
        "title": "СМИ: глава Canada Goose перестал быть миллиардером из-за коронавируса ",
        "additionally": "Генеральный директор и президент Canada Goose Дани Рейсс дает интервью в Нью-Йоркской фондовой бирже в четверг, 16 марта 2017  ",
        "href": "https://ria.ru/20200209/1564459678.html",
        "time": "17:06"
    },
    {
        "title": "Вице-премьер Белоруссии объяснил покупку нефти из РФ по мировым ценам  ",
        "additionally": "Мозырский нефтеперерабатывающий завод ",
        "href": "https://radiosputnik.ria.ru/20200209/1564458536.html",
        "time": "16:05"
    },
    {
        "title": "В Минске не исключили корректировки цены на российский газ ",
        "additionally": "Газораспределительная станция ОАО Газпром ",
        "href": "https://ria.ru/20200209/1564458189.html",
        "time": "15:53"
    },
    {
        "title": "Стоимость биткоина впервые с октября превысила десять тысяч долларов ",
        "additionally": "Монета с логотипом криптовалюты биткоин",
        "href": "https://ria.ru/20200209/1564457904.html",
        "time": "15:46"
    },
    {
        "title": "Белоруссия намерена покупать нефть у России по мировым ценам ",
        "additionally": "Мозырский нефтеперерабатывающий завод в Белоруссии",
        "href": "https://ria.ru/20200209/1564456872.html",
        "time": "15:10"
    },
    {
        "title": "В Минэкономразвития рассказали о мультипликативном эффекте нацпроектов ",
        "additionally": "Максим Решетников",
        "href": "https://ria.ru/20200209/1564456521.html",
        "time": "15:01"
    },
    {
        "title": "Проект \"Самолета\" в новой Москве согласуют после создания рабочих мест ",
        "additionally": "Строительство жилого комплекса ",
        "href": "https://realty.ria.ru/20200209/1564454956.html",
        "time": "13:56"
    }
]